{
  "create": [
    {
      "time": 0.0,
      "target": {
        "type": "-",
        "position": {
          "X": 0.0,
          "Y": 0.0
        },
        "destination": {
          "X": 0.0,
          "Y": 0.0
        },
        "speed": 0.0,
        "health": 0,
        "fdirection": {
          "X": 0.0,
          "Y": 0.0
        },
        "direction": {
          "X": 0.0,
          "Y": 0.0
        },
        "fspeed": 0.0,
        "id": 0
      }
    }
  ],
  "shoot": [],
  "move": [
    {
      "time": 0.0,
      "targetId": 0,
      "direction": {
        "X": 0.0,
        "Y": 0.0
      },
      "destination": {
        "X": 0.0,
        "Y": 0.0
      },
      "fdirection": {
        "X": 0.0,
        "Y": 0.0
      },
      "fspeed": 0.0,
      "speed": 0.0
    }
  ]
}